{
  "special": false,
  "hp": 60,
  "description": "card.gym2-41.description",
  "attacks": [
    {
      "name": "attack.gym2-41.0.name",
      "costs": [
        "PSYCHIC",
        "PSYCHIC",
        "PSYCHIC"
      ],
      "damage": 40,
      "text": "attack.gym2-41.0.description",
      "effects": []
    }
  ],
  "retreat_cost": 2,
  "energies": "GRASS",
  "pokemon_id": 2,
  "ability": {
    "name": "ability.gym2-41.name",
    "description": "ability.gym2-41.description",
    "type": "POWER",
    "effect": {
      "type": "tcg:unimplemented"
    }
  },
  "weakness": {
    "energy": "FIRE",
    "value": 2,
    "modifier": "*"
  },
  "rarity": "tcg:uncommon"
}