{
  "special": false,
  "hp": 90,
  "description": "card.gym2-4.description",
  "attacks": [
    {
      "name": "attack.gym2-4.0.name",
      "costs": [
        "PSYCHIC",
        "PSYCHIC",
        "PSYCHIC"
      ],
      "damage": 0,
      "text": "attack.gym2-4.0.description",
      "effects": []
    },
    {
      "name": "attack.gym2-4.1.name",
      "costs": [
        "PSYCHIC",
        "PSYCHIC",
        "PSYCHIC"
      ],
      "damage": 20,
      "text": "attack.gym2-4.1.description",
      "effects": []
    }
  ],
  "retreat_cost": 2,
  "energies": "GRASS",
  "pokemon_id": 3,
  "weakness": {
    "energy": "FIRE",
    "value": 2,
    "modifier": "*"
  },
  "rarity": "tcg:holo_rare"
}