{
  "id": "Gligar",
  "spawnInfos": [
    {
      "spec": "species:Gligar",
      "stringLocationTypes": [
        "Land"
      ],
      "minLevel": 2,
      "maxLevel": 29,
      "typeID": "pokemon",
      "condition": {
        "times": [
          "AFTERNOON",
          "DUSK",
          "NIGHT"
        ],
        "biomes": [
          "#pixelmon:spawning/swamps",
          "#pixelmon:spawning/redwoods"
        ]
      },
      "rarity": 90.0
    },
    {
      "spec": "species:Gligar",
      "stringLocationTypes": [
        "Land"
      ],
      "minLevel": 2,
      "maxLevel": 29,
      "typeID": "pokemon",
      "condition": {
        "times": [
          "DAY"
        ],
        "biomes": [
          "pixelmon:ultra_desert"
        ]
      },
      "rarity": 100.0
    }
  ]
}
