{
  "id": 27,
  "setId": 1,
  "cardType": "BASIC",
  "isSpecial": false,
  "hp": 50,
  "energy1": "COLORLESS",
  "energy2": null,
  "pokemonId": 83,
  "code": "BASE27",
  "name": "card.BASE27.name",
  "description": "",
  "previousPokemonId": 0,
  "cardAttacks": [
    {
      "card": "BASE27",
      "index": 1,
      "name": "attack.BASE27.1.name",
      "costs": [
        "COLORLESS"
      ],
      "damage": 30,
      "modifier": null,
      "text": "attack.BASE27.1.text",
      "effects": [
        "TAIL-SELF_MISSED",
        "SELF_DISABLED:FOREVER"
      ]
    },
    {
      "card": "BASE27",
      "index": 2,
      "name": "attack.BASE27.2.name",
      "costs": [
        "COLORLESS",
        "COLORLESS",
        "COLORLESS"
      ],
      "damage": 30,
      "modifier": null,
      "text": null,
      "effectsString": null,
      "effects": null
    }
  ],
  "energyResistance": "FIGHTING",
  "resistanceValue": 30,
  "resistanceCardModifier": "Minus",
  "energyWeakness": "LIGHTNING",
  "weaknessValue": 2,
  "weaknessCardModifier": "Multiply",
  "retreatCost": 1,
  "cardRarity": "UNCOMMON",
  "customTexture": null,
  "customTextureX": 0,
  "customTextureY": 0,
  "isHolo": true,
  "effect": null,
  "cardAbility": null
}
