{
	"rewards": {
		"recipes": [
			"pixelmon:decor/clock/gray_clock"
		]
	},
	"criteria": {
		"has_the_recipe": {
			"trigger": "minecraft:recipe_unlocked",
			"conditions": {
				"recipe": "pixelmon:decor/clock/gray_clock"
			}
		},
		"has_clock": {
			"trigger": "minecraft:inventory_changed",
			"conditions": {
				"items": [
					{
            "item": "minecraft:clock"
					}
				]
			}
		},
    "has_dye": {
      "trigger": "minecraft:inventory_changed",
      "conditions": {
        "items": [
          {
            "tag": "forge:dyes/gray"
          }
        ]
      }
    }
	},
	"requirements": [
		[
			"has_the_recipe",
			"has_clock",
      "has_dye"
		]
	]
}
